interception/__init__.py
interception/_ioctl.py
interception/_keycodes.py
interception/_utils.py
interception/beziercurve.py
interception/constants.py
interception/device.py
interception/exceptions.py
interception/inputs.py
interception/interception.py
interception/py.typed
interception/strokes.py
interception_python-1.13.6.dist-info/METADATA
interception_python-1.13.6.dist-info/WHEEL
interception_python-1.13.6.dist-info/top_level.txt
interception_python-1.13.6.dist-info/RECORD
