Metadata-Version: 2.4
Name: interception-python
Version: 1.13.6
Summary: A python port of interception, which hooks into the input event handling mechanisms to simulate inputs without injected flags
Author-email: Kenny Hommel <kennyhommel36@gmail.com>
Project-URL: Homepage, https://github.com/kennyhml/pyinterception
Project-URL: Bug Tracker, https://github.com/kennyhml/pyinterception/issues
Classifier: Programming Language :: Python :: 3
Classifier: License :: OSI Approved :: MIT License
Classifier: Operating System :: OS Independent
Requires-Python: >=3.10
